pdengine/FirstPrinciplesModel.py
pdengine/Model.py
pdengine/PIDController.py
pdengine/ValveModel.py
pdengine/WoodBerryModel.py
pdengine/__init__.py
tests/general_tests_class.py
tests/test_ValveModel.py
tests/test_WoodBerryModel.py
pdengine-0.0.6.dist-info/LICENSE
pdengine-0.0.6.dist-info/METADATA
pdengine-0.0.6.dist-info/WHEEL
pdengine-0.0.6.dist-info/top_level.txt
pdengine-0.0.6.dist-info/RECORD
