Metadata-Version: 2.1
Name: pdengine
Version: 0.0.6
Summary: Process Dynamics Engine
Author-email: Siang Lim <sianglim@gatech.edu>
Project-URL: Homepage, https://github.com/csianglim/pd-engine/
Project-URL: Bug Tracker, https://github.com/csianglim/pd-engine/issues
Classifier: Programming Language :: Python :: 3
Classifier: License :: OSI Approved :: MIT License
Classifier: Operating System :: OS Independent
Requires-Python: >=3.7
License-File: LICENSE
Requires-Dist: control ==0.9.2
Requires-Dist: numpy ==1.23.5
Requires-Dist: noise ==1.2.2
